README.txt
setup.py
docs/HISTORY.txt
docs/LICENSE.ZPL
plone/__init__.py
plone.validatehook.egg-info/PKG-INFO
plone.validatehook.egg-info/SOURCES.txt
plone.validatehook.egg-info/dependency_links.txt
plone.validatehook.egg-info/entry_points.txt
plone.validatehook.egg-info/namespace_packages.txt
plone.validatehook.egg-info/not-zip-safe
plone.validatehook.egg-info/requires.txt
plone.validatehook.egg-info/top_level.txt
plone/validatehook/__init__.py
plone/validatehook/configure.zcml
plone/validatehook/event.py
plone/validatehook/hook.py
plone/validatehook/interfaces.py