Metadata-Version: 1.0
Name: plone.validatehook
Version: 1.0
Summary: Zope 2 publisher validation hook
Home-page: UNKNOWN
Author: Wichert Akkerman
Author-email: wichert@wiggy.net
License: ZPL
Platform: UNKNOWN
Classifier: Environment :: Web Environment
Classifier: Framework :: Zope2
Classifier: License :: OSI Approved :: Zope Public License
Classifier: Programming Language :: Python
Classifier: Topic :: Software Development :: Libraries :: Python Modules
